src/__init__.py
src/client.py
src/database.py
src/main.py
logical_package-1.0.0.dist-info/METADATA
logical_package-1.0.0.dist-info/WHEEL
logical_package-1.0.0.dist-info/top_level.txt
logical_package-1.0.0.dist-info/RECORD
