Metadata-Version: 2.1
Name: logical-package
Version: 1.0.0
Requires-Python: >=3.7, <4
Requires-Dist: pymongo
Requires-Dist: python-binance
